torch_transform_image/__init__.py
torch_transform_image/py.typed
torch_transform_image/transforms_2d.py
torch_transform_image/transforms_3d.py
torch_transform_image-0.1.1.dist-info/METADATA
torch_transform_image-0.1.1.dist-info/WHEEL
torch_transform_image-0.1.1.dist-info/licenses/LICENSE
torch_transform_image-0.1.1.dist-info/RECORD
