Metadata-Version: 2.4
Name: torch-transform-image
Version: 0.1.1
Summary: Real space transformations of 2D/3D images in PyTorch
Project-URL: homepage, https://github.com/teamtomo/torch-transform-image
Project-URL: repository, https://github.com/teamtomo/torch-transform-image
Author-email: Alister Burt <alisterburt@gmail.com>
License: BSD-3-Clause
License-File: LICENSE
Classifier: Development Status :: 3 - Alpha
Classifier: License :: OSI Approved :: BSD License
Classifier: Programming Language :: Python :: 3
Classifier: Programming Language :: Python :: 3.9
Classifier: Programming Language :: Python :: 3.10
Classifier: Programming Language :: Python :: 3.11
Classifier: Programming Language :: Python :: 3.12
Classifier: Programming Language :: Python :: 3.13
Classifier: Typing :: Typed
Requires-Python: >=3.10
Requires-Dist: torch
Requires-Dist: torch-affine-utils
Requires-Dist: torch-grid-utils
Requires-Dist: torch-image-interpolation
Provides-Extra: dev
Requires-Dist: ipython; extra == 'dev'
Requires-Dist: pdbpp; extra == 'dev'
Requires-Dist: rich; extra == 'dev'
Provides-Extra: test
Requires-Dist: pytest; extra == 'test'
Requires-Dist: pytest-cov; extra == 'test'
